{
  "error": {
    "name": "PrismaClientValidationError",
    "message": "\nInvalid `prisma.leg.upsert()` invocation in\nC:\\Users\\djorn\\Downloads\\altidal-frontend\\scripts\\sources\\aviapages.ts:427:28\n\n  424 try {\n  425   await withConcurrency(batch, 6, async (r) => {\n  426     try {\n→ 427       await prisma.leg.upsert({\n              where: {\n                id: \"7e113f0c36637dc2\"\n              },\n              update: {\n                operator: \"aviapages\",\n                fromIata: \"SXM\",\n                toIata: \"TEB\",\n                fromIcao: \"TNCM\",\n                toIcao: \"KTEB\",\n                fromCity: \"Princess Juliana Intl\",\n                toCity: \"Teterboro\",\n                fromName: \"Princess Juliana Intl\",\n                toName: \"Teterboro\",\n                departAt: \"2025-12-20T00:00:00.000Z\",\n                acType: \"Gulfstream G650ER\",\n                acClass: \"Heavy Jet\",\n                seats: null,\n                priceUSD: 0,\n                url: \"https://aviapages.com/charter_at_hand/\",\n                notes: \"20-12-2025 00:00 → 21-12-2025 00:00 | Price on Request\"\n              },\n              create: {\n                id: \"7e113f0c36637dc2\",\n                operator: \"aviapages\",\n                fromIata: \"SXM\",\n                toIata: \"TEB\",\n                fromIcao: \"TNCM\",\n                toIcao: \"KTEB\",\n                fromCity: \"Princess Juliana Intl\",\n                toCity: \"Teterboro\",\n                fromName: \"Princess Juliana Intl\",\n                toName: \"Teterboro\",\n                departAt: \"2025-12-20T00:00:00.000Z\",\n                acType: \"Gulfstream G650ER\",\n                acClass: \"Heavy Jet\",\n                priceUSD: 0,\n                url: \"https://aviapages.com/charter_at_hand/\",\n                notes: \"20-12-2025 00:00 → 21-12-2025 00:00 | Price on Request\",\n            +   seats: Int\n              }\n            })\n\nArgument `seats` must not be null.",
    "meta": null
  },
  "row": {
    "id": "7e113f0c36637dc2",
    "operator": "aviapages",
    "fromIata": "SXM",
    "toIata": "TEB",
    "fromIcao": "TNCM",
    "toIcao": "KTEB",
    "fromCity": "Princess Juliana Intl",
    "toCity": "Teterboro",
    "fromName": "Princess Juliana Intl",
    "toName": "Teterboro",
    "departAt": "2025-12-20T00:00:00.000Z",
    "acType": "Gulfstream G650ER",
    "acClass": "Heavy Jet",
    "seats": null,
    "priceUSD": 0,
    "url": "https://aviapages.com/charter_at_hand/",
    "notes": "20-12-2025 00:00 → 21-12-2025 00:00 | Price on Request"
  }
}