{
  "error": {
    "name": "PrismaClientValidationError",
    "message": "\nInvalid `prisma.leg.upsert()` invocation in\nC:\\Users\\djorn\\Downloads\\altidal-frontend\\scripts\\sources\\aviapages.ts:427:28\n\n  424 try {\n  425   await withConcurrency(batch, 6, async (r) => {\n  426     try {\n→ 427       await prisma.leg.upsert({\n              where: {\n                id: \"f3e6a0fd961104af\"\n              },\n              update: {\n                operator: \"aviapages\",\n                fromIata: \"SCF\",\n                toIata: \"SFO\",\n                fromIcao: \"KSDL\",\n                toIcao: \"KSFO\",\n                fromCity: \"Scottsdale\",\n                toCity: \"San Francisco Intl\",\n                fromName: \"Scottsdale\",\n                toName: \"San Francisco Intl\",\n                departAt: \"2025-12-28T00:00:00.000Z\",\n                acType: \"Cessna Citation Excel\",\n                acClass: \"Midsize Jet\",\n                seats: null,\n                priceUSD: 5000,\n                url: \"https://aviapages.com/charter_at_hand/\",\n                notes: \"28-12-2025 00:00 → 28-12-2025 02:00\"\n              },\n              create: {\n                id: \"f3e6a0fd961104af\",\n                operator: \"aviapages\",\n                fromIata: \"SCF\",\n                toIata: \"SFO\",\n                fromIcao: \"KSDL\",\n                toIcao: \"KSFO\",\n                fromCity: \"Scottsdale\",\n                toCity: \"San Francisco Intl\",\n                fromName: \"Scottsdale\",\n                toName: \"San Francisco Intl\",\n                departAt: \"2025-12-28T00:00:00.000Z\",\n                acType: \"Cessna Citation Excel\",\n                acClass: \"Midsize Jet\",\n                priceUSD: 5000,\n                url: \"https://aviapages.com/charter_at_hand/\",\n                notes: \"28-12-2025 00:00 → 28-12-2025 02:00\",\n            +   seats: Int\n              }\n            })\n\nArgument `seats` must not be null.",
    "meta": null
  },
  "row": {
    "id": "f3e6a0fd961104af",
    "operator": "aviapages",
    "fromIata": "SCF",
    "toIata": "SFO",
    "fromIcao": "KSDL",
    "toIcao": "KSFO",
    "fromCity": "Scottsdale",
    "toCity": "San Francisco Intl",
    "fromName": "Scottsdale",
    "toName": "San Francisco Intl",
    "departAt": "2025-12-28T00:00:00.000Z",
    "acType": "Cessna Citation Excel",
    "acClass": "Midsize Jet",
    "seats": null,
    "priceUSD": 5000,
    "url": "https://aviapages.com/charter_at_hand/",
    "notes": "28-12-2025 00:00 → 28-12-2025 02:00"
  }
}