{
  "error": {
    "name": "PrismaClientValidationError",
    "message": "\nInvalid `prisma.leg.upsert()` invocation in\nC:\\Users\\djorn\\Downloads\\altidal-frontend\\scripts\\sources\\aviapages.ts:427:28\n\n  424 try {\n  425   await withConcurrency(batch, 6, async (r) => {\n  426     try {\n→ 427       await prisma.leg.upsert({\n              where: {\n                id: \"f4c77c45458b0af1\"\n              },\n              update: {\n                operator: \"aviapages\",\n                fromIata: \"VCE\",\n                toIata: \"LIN\",\n                fromIcao: \"LIPZ\",\n                toIcao: \"LIML\",\n                fromCity: \"Tessera\",\n                toCity: \"Linate\",\n                fromName: \"Tessera\",\n                toName: \"Linate\",\n                departAt: \"2025-10-24T10:35:00.000Z\",\n                acType: \"Cessna Citation XLS+\",\n                acClass: \"Midsize Jet\",\n                seats: null,\n                priceUSD: 0,\n                url: \"https://aviapages.com/charter_at_hand/\",\n                notes: \"24-10-2025 10:35 → 24-10-2025 11:28 | Price on Request\"\n              },\n              create: {\n                id: \"f4c77c45458b0af1\",\n                operator: \"aviapages\",\n                fromIata: \"VCE\",\n                toIata: \"LIN\",\n                fromIcao: \"LIPZ\",\n                toIcao: \"LIML\",\n                fromCity: \"Tessera\",\n                toCity: \"Linate\",\n                fromName: \"Tessera\",\n                toName: \"Linate\",\n                departAt: \"2025-10-24T10:35:00.000Z\",\n                acType: \"Cessna Citation XLS+\",\n                acClass: \"Midsize Jet\",\n                priceUSD: 0,\n                url: \"https://aviapages.com/charter_at_hand/\",\n                notes: \"24-10-2025 10:35 → 24-10-2025 11:28 | Price on Request\",\n            +   seats: Int\n              }\n            })\n\nArgument `seats` must not be null.",
    "meta": null
  },
  "row": {
    "id": "f4c77c45458b0af1",
    "operator": "aviapages",
    "fromIata": "VCE",
    "toIata": "LIN",
    "fromIcao": "LIPZ",
    "toIcao": "LIML",
    "fromCity": "Tessera",
    "toCity": "Linate",
    "fromName": "Tessera",
    "toName": "Linate",
    "departAt": "2025-10-24T10:35:00.000Z",
    "acType": "Cessna Citation XLS+",
    "acClass": "Midsize Jet",
    "seats": null,
    "priceUSD": 0,
    "url": "https://aviapages.com/charter_at_hand/",
    "notes": "24-10-2025 10:35 → 24-10-2025 11:28 | Price on Request"
  }
}