{
  "error": {
    "name": "PrismaClientValidationError",
    "message": "\nInvalid `prisma.leg.upsert()` invocation in\nC:\\Users\\djorn\\Downloads\\altidal-frontend\\scripts\\sources\\flyvictor.ts:384:28\n\n  381 try {\n  382   await withConcurrency(batch, 6, async (r) => {\n  383     try {\n→ 384       await prisma.leg.upsert({\n              where: {\n                id: \"4eb266734a1817ef\"\n              },\n              update: {\n                operator: \"flyvictor\",\n                fromIata: \"TEB\",\n                toIata: \"VNY\",\n                fromName: \"TEB\",\n                toName: \"VNY\",\n                fromCity: \"TEB\",\n                toCity: \"VNY\",\n                departAt: null,\n                acType: \"Unknown\",\n                acClass: \"Unknown\",\n                priceUSD: 0,\n                url: \"https://www.flyvictor.com/en-us/flights/\"\n              },\n              create: {\n                id: \"4eb266734a1817ef\",\n                operator: \"flyvictor\",\n                fromIata: \"TEB\",\n                toIata: \"VNY\",\n                fromName: \"TEB\",\n                toName: \"VNY\",\n                fromCity: \"TEB\",\n                toCity: \"VNY\",\n                departAt: null,\n                acType: \"Unknown\",\n                acClass: \"Unknown\",\n                priceUSD: 0,\n                url: \"https://www.flyvictor.com/en-us/flights/\",\n            +   seats: Int\n              }\n            })\n\nArgument `seats` is missing.",
    "meta": null
  },
  "row": {
    "id": "4eb266734a1817ef",
    "operator": "flyvictor",
    "fromIata": "TEB",
    "toIata": "VNY",
    "fromName": "TEB",
    "toName": "VNY",
    "fromCity": "TEB",
    "toCity": "VNY",
    "departAt": null,
    "acType": "Unknown",
    "acClass": "Unknown",
    "priceUSD": 0,
    "url": "https://www.flyvictor.com/en-us/flights/"
  }
}