{
  "error": {
    "name": "PrismaClientValidationError",
    "message": "\nInvalid `prisma.leg.upsert()` invocation in\nC:\\Users\\djorn\\Downloads\\altidal-frontend\\scripts\\sources\\flyvictor.ts:527:28\n\n  524 try {\n  525   await withConcurrency(batch, 6, async (r) => {\n  526     try {\n→ 527       await prisma.leg.upsert({\n              where: {\n                id: \"0d6dcdd0336ec1ba\"\n              },\n              update: {\n                operator: \"flyvictor\",\n                fromIata: \"TUL\",\n                toIata: \"LAS\",\n                fromName: \"TUL\",\n                toName: \"LAS\",\n                departAt: \"2025-10-26T00:00:00.000Z\",\n                priceUSD: 16781,\n                url: \"https://www.flyvictor.com/en-us/flights/\"\n              },\n              create: {\n                id: \"0d6dcdd0336ec1ba\",\n                operator: \"flyvictor\",\n                fromIata: \"TUL\",\n                toIata: \"LAS\",\n                fromName: \"TUL\",\n                toName: \"LAS\",\n                departAt: \"2025-10-26T00:00:00.000Z\",\n                priceUSD: 16781,\n                url: \"https://www.flyvictor.com/en-us/flights/\",\n            +   fromCity: String\n              }\n            })\n\nArgument `fromCity` is missing.",
    "meta": null
  },
  "row": {
    "id": "0d6dcdd0336ec1ba",
    "operator": "flyvictor",
    "fromIata": "TUL",
    "toIata": "LAS",
    "fromName": "TUL",
    "toName": "LAS",
    "departAt": "2025-10-26T00:00:00.000Z",
    "priceUSD": 16781,
    "url": "https://www.flyvictor.com/en-us/flights/"
  }
}